retrosys/__init__.py
retrosys/core/__init__.py
retrosys/core/dependency_injection/__init__.py
retrosys/core/dependency_injection/container.py
retrosys/core/dependency_injection/decorators.py
retrosys/core/dependency_injection/errors.py
retrosys/core/dependency_injection/lazy.py
retrosys/core/dependency_injection/module.py
retrosys/core/dependency_injection/project_types.py
retrosys/core/dependency_injection/scope.py
retrosys/core/dependency_injection/service_descriptor.py
retrosys_core-0.1.0.dist-info/licenses/LICENSE
retrosys_core-0.1.0.dist-info/METADATA
retrosys_core-0.1.0.dist-info/WHEEL
retrosys_core-0.1.0.dist-info/top_level.txt
retrosys_core-0.1.0.dist-info/RECORD
