Metadata-Version: 2.4
Name: retrosys-core
Version: 0.1.0
Summary: Yet another Python dependency injection framework
Home-page: https://github.com/arashafaghi/retrosys_core
Author: RetroSys
Author-email: afaghi@gmail.com
Project-URL: Bug Tracker, https://github.com/arashafaghi/retrosys_core/issues
Project-URL: Documentation, https://retrosys-core.readthedocs.io/en/latest/
Classifier: Programming Language :: Python :: 3
Classifier: License :: OSI Approved :: MIT License
Classifier: Operating System :: OS Independent
Requires-Python: >=3.6
License-File: LICENSE
Provides-Extra: docs
Requires-Dist: sphinx>=7.0.0; extra == "docs"
Requires-Dist: sphinx-rtd-theme>=2.0.0; extra == "docs"
Requires-Dist: sphinx-autodoc-typehints>=1.12.0; extra == "docs"
Requires-Dist: myst-parser>=0.15.0; extra == "docs"
Dynamic: author
Dynamic: author-email
Dynamic: classifier
Dynamic: description
Dynamic: description-content-type
Dynamic: home-page
Dynamic: license-file
Dynamic: project-url
Dynamic: provides-extra
Dynamic: requires-python
Dynamic: summary
